CHANGES.rst
CONTRIBUTING.rst
LICENSE
MANIFEST.in
README.rst
pytest.ini
run-tests.sh
setup.cfg
setup.py
docs/sphinx/Makefile
docs/sphinx/conf.py
docs/sphinx/contributing.rst
docs/sphinx/history.rst
docs/sphinx/index.rst
docs/sphinx/license.rst
docs/sphinx/make.bat
docs/sphinx/readme.rst
docs/sphinx/_static/stac.css
docs/sphinx/img/favicon.ico
docs/sphinx/img/logo-bdc.png
examples/bbox.py
examples/ex-01.py
stac/__init__.py
stac/catalog.py
stac/cli.py
stac/collection.py
stac/common.py
stac/item.py
stac/stac.py
stac/utils.py
stac/version.py
stac.py.egg-info/PKG-INFO
stac.py.egg-info/SOURCES.txt
stac.py.egg-info/dependency_links.txt
stac.py.egg-info/entry_points.txt
stac.py.egg-info/not-zip-safe
stac.py.egg-info/requires.txt
stac.py.egg-info/top_level.txt
stac/jsonschemas/0.7.0/catalog.json
stac/jsonschemas/0.7.0/collection.json
stac/jsonschemas/0.7.0/geojson.json
stac/jsonschemas/0.7.0/item.json
stac/jsonschemas/0.8.0/catalog.json
stac/jsonschemas/0.8.0/collection.json
stac/jsonschemas/0.8.0/item.json
stac/jsonschemas/0.8.0/itemcollection.json
stac/jsonschemas/0.8.1/catalog.json
stac/jsonschemas/0.8.1/collection.json
stac/jsonschemas/0.8.1/item.json
stac/jsonschemas/0.8.1/itemcollection.json
stac/jsonschemas/0.9.0/basics.json
stac/jsonschemas/0.9.0/catalog.json
stac/jsonschemas/0.9.0/collection.json
stac/jsonschemas/0.9.0/datetimerange.json
stac/jsonschemas/0.9.0/instrument.json
stac/jsonschemas/0.9.0/item.json
stac/jsonschemas/0.9.0/itemcollection.json
stac/jsonschemas/0.9.0/licensing.json
stac/jsonschemas/0.9.0/metadata.json
stac/jsonschemas/0.9.0/provider.json
stac/templates/collection.html
stac/templates/item.html
stac/templates/itemcollection.html
tests/__init__.py
tests/stac_tests/__init__.py
tests/stac_tests/test_stac.py
tests/stac_tests/jsons/0.7.0/catalog.json
tests/stac_tests/jsons/0.7.0/collection.json
tests/stac_tests/jsons/0.7.0/items.json
tests/stac_tests/jsons/0.8.0/catalog.json
tests/stac_tests/jsons/0.8.0/collection.json
tests/stac_tests/jsons/0.8.0/items.json
tests/stac_tests/jsons/0.8.1/catalog.json
tests/stac_tests/jsons/0.8.1/collection.json
tests/stac_tests/jsons/0.8.1/items.json
tests/stac_tests/jsons/0.9.0/catalog.json
