Metadata-Version: 2.1
Name: stac.py
Version: 0.9.0.post12
Summary: Python Client Library for STAC.
Home-page: https://github.com/brazil-data-cube/stac.py
Author: Brazil Data Cube Team
Author-email: brazildatacube@inpe.br
License: MIT
Keywords: SpatioTemporal Asset Catalog,stac,earth-observation,geospatial,gis
Platform: any
Classifier: Development Status :: 3 - Alpha
Classifier: Environment :: Web Environment
Classifier: Intended Audience :: Education
Classifier: Intended Audience :: Science/Research
Classifier: License :: OSI Approved :: MIT License
Classifier: Operating System :: OS Independent
Classifier: Programming Language :: Python :: 3.7
Classifier: Topic :: Software Development :: Libraries :: Python Modules
Classifier: Topic :: Scientific/Engineering :: GIS
Provides-Extra: docs
Provides-Extra: examples
Provides-Extra: oauth
Provides-Extra: tests
Provides-Extra: tqdm
Provides-Extra: geo
Provides-Extra: all
